<archimate:ArchimateDiagramModel
    xmlns:xsi="http://www.w3.org/2001/XMLSchema-instance"
    xmlns:archimate="http://www.archimatetool.com/archimate"
    name="Service Management - Mapa"
    id="id-27fe7a27025341f6a2d8c65d277afed8"
    documentation="Visualizador de alarmas de servicios IP de Backbone"
    connectionRouterType="2">
  <children
      xsi:type="archimate:DiagramModelArchimateObject"
      id="id-c6a65c05b4f34bceaeb264371fb9e7d4"
      font="1|Lucida Grande|13.0|1|COCOA|1|LucidaGrande-Bold"
      textAlignment="1">
    <bounds
        x="3228"
        y="118"
        width="336"
        height="732"/>
    <children
        xsi:type="archimate:DiagramModelArchimateObject"
        id="id-e56562534a974562a6beb86a24ad6c0b"
        fillColor="#b3fffd">
      <bounds
          x="24"
          y="384"
          width="120"
          height="55"/>
      <archimateElement
          xsi:type="archimate:ApplicationComponent"
          href="ApplicationComponent_id-19a0e9fe55b84af58fbc07430fabf05a.xml#id-19a0e9fe55b84af58fbc07430fabf05a"/>
    </children>
    <children
        xsi:type="archimate:DiagramModelArchimateObject"
        id="id-a728bebc507f4560862332c06f62a66f">
      <bounds
          x="24"
          y="480"
          width="120"
          height="55"/>
      <archimateElement
          xsi:type="archimate:ApplicationComponent"
          href="ApplicationComponent_id-6f1c57e283a140febc59bda5115e2727.xml#id-6f1c57e283a140febc59bda5115e2727"/>
    </children>
    <children
        xsi:type="archimate:DiagramModelArchimateObject"
        id="id-4e734361f12d40df97ba478f4ee3c7c6">
      <bounds
          x="180"
          y="384"
          width="120"
          height="55"/>
      <archimateElement
          xsi:type="archimate:ApplicationComponent"
          href="ApplicationComponent_id-bac49e4afac8431db75d0653821f9231.xml#id-bac49e4afac8431db75d0653821f9231"/>
    </children>
    <children
        xsi:type="archimate:DiagramModelArchimateObject"
        id="id-247eeb44aa9241dd9ec08bcf33fffdd3">
      <bounds
          x="180"
          y="276"
          width="120"
          height="55"/>
      <archimateElement
          xsi:type="archimate:ApplicationComponent"
          href="ApplicationComponent_id-11e950560c984db884c42edfc6f4a424.xml#id-11e950560c984db884c42edfc6f4a424"/>
    </children>
    <children
        xsi:type="archimate:DiagramModelArchimateObject"
        id="id-4dc3f497c27b4100b9b804943290a6b2">
      <bounds
          x="180"
          y="480"
          width="120"
          height="55"/>
      <archimateElement
          xsi:type="archimate:ApplicationComponent"
          href="ApplicationComponent_id-c35e1cba01a34e78bdfab7203ade5999.xml#id-c35e1cba01a34e78bdfab7203ade5999"/>
    </children>
    <children
        xsi:type="archimate:DiagramModelArchimateObject"
        id="id-2c0e6e0373824429bbba3f13c58ac70a">
      <bounds
          x="24"
          y="564"
          width="120"
          height="55"/>
      <archimateElement
          xsi:type="archimate:ApplicationComponent"
          href="ApplicationComponent_id-0e9e03d14fe9453084c55f58e512e0d5.xml#id-0e9e03d14fe9453084c55f58e512e0d5"/>
    </children>
    <children
        xsi:type="archimate:DiagramModelArchimateObject"
        id="id-3c266079d218494280c9b4a0b1aaff1d">
      <bounds
          x="180"
          y="564"
          width="120"
          height="55"/>
      <archimateElement
          xsi:type="archimate:ApplicationComponent"
          href="ApplicationComponent_id-6ce1ce62d9754eab963897a951b3a227.xml#id-6ce1ce62d9754eab963897a951b3a227"/>
    </children>
    <children
        xsi:type="archimate:DiagramModelArchimateObject"
        id="id-f30dcb3a03874365856e9c15204f4fa4">
      <bounds
          x="24"
          y="648"
          width="120"
          height="55"/>
      <archimateElement
          xsi:type="archimate:ApplicationComponent"
          href="ApplicationComponent_id-ff744ac9c12547e6917e6307519125ed.xml#id-ff744ac9c12547e6917e6307519125ed"/>
    </children>
    <archimateElement
        xsi:type="archimate:Grouping"
        href="Grouping_id-18bc70aa48dc499490ae88050856142d.xml#id-18bc70aa48dc499490ae88050856142d"/>
  </children>
  <children
      xsi:type="archimate:DiagramModelArchimateObject"
      id="id-df7850cef79740f785f76520dd1aa666"
      font="1|Lucida Grande|13.0|1|COCOA|1|LucidaGrande-Bold"
      textAlignment="1">
    <bounds
        x="2592"
        y="121"
        width="324"
        height="734"/>
    <children
        xsi:type="archimate:DiagramModelArchimateObject"
        id="id-71c851aaa5f246c6ab826ef2dcbad45c"
        textPosition="1">
      <bounds
          x="180"
          y="72"
          width="120"
          height="55"/>
      <archimateElement
          xsi:type="archimate:Capability"
          href="Capability_id-ee340f29e2864b299f6bfdcebd31ebab.xml#id-ee340f29e2864b299f6bfdcebd31ebab"/>
    </children>
    <children
        xsi:type="archimate:DiagramModelArchimateObject"
        id="id-e23c097f62544077a5151d786e82999a">
      <bounds
          x="180"
          y="276"
          width="120"
          height="55"/>
      <archimateElement
          xsi:type="archimate:ApplicationComponent"
          href="ApplicationComponent_id-23f5e1a05d84474ba1459dba0d9cdb9e.xml#id-23f5e1a05d84474ba1459dba0d9cdb9e"/>
    </children>
    <children
        xsi:type="archimate:DiagramModelArchimateObject"
        id="id-73fcc8aac5f14347aff3ab1cd498c4dc"
        fillColor="#b4fffe">
      <bounds
          x="180"
          y="420"
          width="120"
          height="55"/>
      <archimateElement
          xsi:type="archimate:ApplicationComponent"
          href="ApplicationComponent_id-1b0828e3f4e0412c8ca04d8534198989.xml#id-1b0828e3f4e0412c8ca04d8534198989"/>
    </children>
    <archimateElement
        xsi:type="archimate:Grouping"
        href="Grouping_id-83c80912a5424038aaf3d1fc75496cb7.xml#id-83c80912a5424038aaf3d1fc75496cb7"/>
  </children>
  <children
      xsi:type="archimate:DiagramModelArchimateObject"
      id="id-a3228b2dee174a28a72f5c6a7af180c9"
      font="1|Lucida Grande|13.0|1|COCOA|1|LucidaGrande-Bold"
      textAlignment="1">
    <bounds
        x="-780"
        y="120"
        width="324"
        height="732"/>
    <children
        xsi:type="archimate:DiagramModelArchimateObject"
        id="id-dd59040ac92e492c86a89d6c5891c18a">
      <bounds
          x="168"
          y="384"
          width="120"
          height="55"/>
      <archimateElement
          xsi:type="archimate:ApplicationComponent"
          href="ApplicationComponent_id-01ad721b9ed04ed7aa49e6b15c622a71.xml#id-01ad721b9ed04ed7aa49e6b15c622a71"/>
    </children>
    <archimateElement
        xsi:type="archimate:Grouping"
        href="Grouping_id-573f5e2a11ba42789dc0bf9bbc0a7c6c.xml#id-573f5e2a11ba42789dc0bf9bbc0a7c6c"/>
  </children>
  <children
      xsi:type="archimate:DiagramModelArchimateObject"
      id="id-910e6d7fee1b4e7e9ec97c6ad2ec94a2"
      font="1|Lucida Grande|13.0|1|COCOA|1|LucidaGrande-Bold"
      textAlignment="1">
    <bounds
        x="2928"
        y="118"
        width="284"
        height="735"/>
    <children
        xsi:type="archimate:DiagramModelArchimateObject"
        id="id-a950298d39364d429d5f5607b134f0d2">
      <features
          name="labelExpression"
          value="BPM&#xA;Portal"/>
      <bounds
          x="12"
          y="276"
          width="120"
          height="55"/>
      <archimateElement
          xsi:type="archimate:ApplicationComponent"
          href="ApplicationComponent_id-53fd20a50907455aa8a4863564c196c7.xml#id-53fd20a50907455aa8a4863564c196c7"/>
    </children>
    <archimateElement
        xsi:type="archimate:Grouping"
        href="Grouping_id-2b96d05b6fb74eba920494eda898033c.xml#id-2b96d05b6fb74eba920494eda898033c"/>
  </children>
  <children
      xsi:type="archimate:DiagramModelArchimateObject"
      id="id-9f5705bb501c42db97e11d089027a508"
      font="1|Lucida Grande|13.0|1|COCOA|1|LucidaGrande-Bold"
      textAlignment="1">
    <bounds
        x="-444"
        y="120"
        width="432"
        height="732"/>
    <children
        xsi:type="archimate:DiagramModelArchimateObject"
        id="id-3f7c0feffa36487091bace0e560d95ae"
        fillColor="#b3fffd">
      <bounds
          x="300"
          y="384"
          width="120"
          height="55"/>
      <archimateElement
          xsi:type="archimate:ApplicationComponent"
          href="ApplicationComponent_id-b8493ae78afd4fde9d63d298b3ee43d5.xml#id-b8493ae78afd4fde9d63d298b3ee43d5"/>
    </children>
    <children
        xsi:type="archimate:DiagramModelArchimateObject"
        id="id-d8a00fccd24a49339b0c9edcd4fd5a45">
      <bounds
          x="156"
          y="384"
          width="120"
          height="55"/>
      <archimateElement
          xsi:type="archimate:ApplicationComponent"
          href="ApplicationComponent_id-779b5506314447aeb9310e7b2fcdd8ef.xml#id-779b5506314447aeb9310e7b2fcdd8ef"/>
    </children>
    <children
        xsi:type="archimate:DiagramModelArchimateObject"
        id="id-1217e6f0aabb467387b0a2a419d1ef2e">
      <bounds
          x="12"
          y="276"
          width="120"
          height="55"/>
      <archimateElement
          xsi:type="archimate:ApplicationComponent"
          href="ApplicationComponent_id-5b9f62de4b374e0d810cb6f506875b39.xml#id-5b9f62de4b374e0d810cb6f506875b39"/>
    </children>
    <children
        xsi:type="archimate:DiagramModelArchimateObject"
        id="id-949a52b99bcc46be80ccfff9f56010b7"
        textPosition="1">
      <bounds
          x="12"
          y="72"
          width="408"
          height="55"/>
      <archimateElement
          xsi:type="archimate:Capability"
          href="Capability_id-09463276bb814b0a870b34efd5e3f208.xml#id-09463276bb814b0a870b34efd5e3f208"/>
    </children>
    <children
        xsi:type="archimate:DiagramModelArchimateObject"
        id="id-1e29d5c7d5af426eb9a7910a5d92d641">
      <bounds
          x="12"
          y="480"
          width="120"
          height="55"/>
      <archimateElement
          xsi:type="archimate:ApplicationComponent"
          href="ApplicationComponent_id-5fdbcec5816543d69e8eca459b161183.xml#id-5fdbcec5816543d69e8eca459b161183"/>
    </children>
    <archimateElement
        xsi:type="archimate:Grouping"
        href="Grouping_id-a31811e2818b42ffbfc9e976326e7130.xml#id-a31811e2818b42ffbfc9e976326e7130"/>
  </children>
  <children
      xsi:type="archimate:DiagramModelArchimateObject"
      id="id-ae3c99b4717146e7bab75a6d61ee6daa"
      font="1|Lucida Grande|13.0|1|COCOA|1|LucidaGrande-Bold"
      textAlignment="1">
    <bounds
        y="122"
        width="709"
        height="734"/>
    <children
        xsi:type="archimate:DiagramModelArchimateObject"
        id="id-bcfd2bc00b3f4d26935e6309941bd743"
        fillColor="#b4fffe">
      <bounds
          x="576"
          y="276"
          width="120"
          height="55"/>
      <archimateElement
          xsi:type="archimate:ApplicationComponent"
          href="ApplicationComponent_id-abb1b371ec5f43c98372c5acb7021cb4.xml#id-abb1b371ec5f43c98372c5acb7021cb4"/>
    </children>
    <children
        xsi:type="archimate:DiagramModelArchimateObject"
        id="id-64add531e1ee43788a1ee75a57eaf598">
      <bounds
          x="576"
          y="384"
          width="120"
          height="55"/>
      <archimateElement
          xsi:type="archimate:ApplicationComponent"
          href="ApplicationComponent_id-9cd4e093e39d499f809d2d45f9cc5704.xml#id-9cd4e093e39d499f809d2d45f9cc5704"/>
    </children>
    <children
        xsi:type="archimate:DiagramModelArchimateObject"
        id="id-8d0f0d2c748942568bc0359f3251f6c9">
      <bounds
          x="12"
          y="276"
          width="120"
          height="55"/>
      <archimateElement
          xsi:type="archimate:ApplicationComponent"
          href="ApplicationComponent_id-efcfdc4aa474419084cea6e20de9ae70.xml#id-efcfdc4aa474419084cea6e20de9ae70"/>
    </children>
    <archimateElement
        xsi:type="archimate:Grouping"
        href="Grouping_id-a9b61f3a13b349a890e77f9d117ff3eb.xml#id-a9b61f3a13b349a890e77f9d117ff3eb"/>
  </children>
  <children
      xsi:type="archimate:DiagramModelArchimateObject"
      id="id-d55ea64ad656425789c736836bf73662"
      font="1|Lucida Grande|13.0|1|COCOA|1|LucidaGrande-Bold"
      textAlignment="1">
    <bounds
        x="720"
        y="120"
        width="1848"
        height="734"/>
    <children
        xsi:type="archimate:DiagramModelArchimateObject"
        id="id-f6253f7011d94245b0577431b3744ea1"
        textPosition="1">
      <bounds
          x="1572"
          y="72"
          width="120"
          height="55"/>
      <archimateElement
          xsi:type="archimate:Capability"
          href="Capability_id-8496df2001f0479fae1c8118b3f3f555.xml#id-8496df2001f0479fae1c8118b3f3f555"/>
    </children>
    <children
        xsi:type="archimate:DiagramModelArchimateObject"
        id="id-ebc24b13ca2147b1a365cdd0f7ea99d9"
        textPosition="1">
      <bounds
          x="12"
          y="72"
          width="564"
          height="55"/>
      <archimateElement
          xsi:type="archimate:Capability"
          href="Capability_id-8f41ab9f4afd452db1d1aba00e0de836.xml#id-8f41ab9f4afd452db1d1aba00e0de836"/>
    </children>
    <children
        xsi:type="archimate:DiagramModelArchimateObject"
        id="id-4f3c6bbe33b740878b1be8d90cfddf8a"
        fillColor="#2cfbeb">
      <bounds
          x="1572"
          y="274"
          width="120"
          height="55"/>
      <archimateElement
          xsi:type="archimate:ApplicationComponent"
          href="ApplicationComponent_id-a412752ba6fb4fa8932537f50b70dfe0.xml#id-a412752ba6fb4fa8932537f50b70dfe0"/>
    </children>
    <children
        xsi:type="archimate:DiagramModelArchimateObject"
        id="id-067597d182e1431bafdceab194e4623a">
      <bounds
          y="276"
          width="120"
          height="55"/>
      <archimateElement
          xsi:type="archimate:ApplicationComponent"
          href="ApplicationComponent_id-3c77cc41beaa4cc5b1b7b1dc6eeb54e4.xml#id-3c77cc41beaa4cc5b1b7b1dc6eeb54e4"/>
    </children>
    <children
        xsi:type="archimate:DiagramModelArchimateObject"
        id="id-505ab653f0e7493ca3b0cb32199ad4a6">
      <bounds
          y="384"
          width="120"
          height="55"/>
      <archimateElement
          xsi:type="archimate:ApplicationComponent"
          href="ApplicationComponent_id-78a27c9cfacf47f187c5e09025f58aaa.xml#id-78a27c9cfacf47f187c5e09025f58aaa"/>
    </children>
    <children
        xsi:type="archimate:DiagramModelArchimateObject"
        id="id-236700ffae57478d97367260a0a2b15a">
      <bounds
          x="145"
          y="384"
          width="120"
          height="55"/>
      <archimateElement
          xsi:type="archimate:ApplicationComponent"
          href="ApplicationComponent_id-6e10fcbe84f04e509aaf6a54d3dd3efe.xml#id-6e10fcbe84f04e509aaf6a54d3dd3efe"/>
    </children>
    <children
        xsi:type="archimate:DiagramModelArchimateObject"
        id="id-4b830ead92a547ca9976d64ab7c8f277">
      <bounds
          x="288"
          y="384"
          width="120"
          height="55"/>
      <archimateElement
          xsi:type="archimate:ApplicationComponent"
          href="ApplicationComponent_id-ad29c82198534ff5a5e703f2cae0d609.xml#id-ad29c82198534ff5a5e703f2cae0d609"/>
    </children>
    <children
        xsi:type="archimate:DiagramModelArchimateObject"
        id="id-690b5d020b13448baebe146773df073d">
      <features
          name="labelExpression"
          value="GCR&#xA;Console"/>
      <bounds
          x="432"
          y="384"
          width="120"
          height="55"/>
      <archimateElement
          xsi:type="archimate:ApplicationComponent"
          href="ApplicationComponent_id-f6bd76e4ddef432c992198a070513aae.xml#id-f6bd76e4ddef432c992198a070513aae"/>
    </children>
    <children
        xsi:type="archimate:DiagramModelArchimateObject"
        id="id-45222a504bbb4313b5400489223b378b">
      <bounds
          x="145"
          y="276"
          width="120"
          height="55"/>
      <archimateElement
          xsi:type="archimate:ApplicationComponent"
          href="ApplicationComponent_id-ad9802f2b07b4a3b96a50c0163cb2f28.xml#id-ad9802f2b07b4a3b96a50c0163cb2f28"/>
    </children>
    <children
        xsi:type="archimate:DiagramModelArchimateObject"
        id="id-3ca19ae59a1843acb20898aac4251653"
        fillColor="#b4fffe">
      <bounds
          x="432"
          y="276"
          width="120"
          height="55"/>
      <archimateElement
          xsi:type="archimate:ApplicationComponent"
          href="ApplicationComponent_id-cdf51614ae9f4960abdce3c1c48024e2.xml#id-cdf51614ae9f4960abdce3c1c48024e2"/>
    </children>
    <children
        xsi:type="archimate:DiagramModelArchimateObject"
        id="id-1055dd49f87e448c979a5b1030f047a2">
      <bounds
          x="145"
          y="480"
          width="120"
          height="55"/>
      <archimateElement
          xsi:type="archimate:ApplicationComponent"
          href="ApplicationComponent_id-ffb7549c5170468da83c7fa0a6cd8d8c.xml#id-ffb7549c5170468da83c7fa0a6cd8d8c"/>
    </children>
    <children
        xsi:type="archimate:DiagramModelArchimateObject"
        id="id-cf7f656494b34e09b53a0d5bf8aa3a2a"
        fillColor="#b4fffe">
      <bounds
          x="288"
          y="276"
          width="120"
          height="55"/>
      <archimateElement
          xsi:type="archimate:ApplicationComponent"
          href="ApplicationComponent_id-b3441c82249d4a4d996dafe06af7ba84.xml#id-b3441c82249d4a4d996dafe06af7ba84"/>
    </children>
    <children
        xsi:type="archimate:DiagramModelArchimateObject"
        id="id-ace163409bbe43ccb1297b18ec1ac756"
        fillColor="#2cfcec">
      <bounds
          y="480"
          width="120"
          height="55"/>
      <archimateElement
          xsi:type="archimate:ApplicationComponent"
          href="ApplicationComponent_id-83bf0ba25e3b4879bedbc9dcf9ad7674.xml#id-83bf0ba25e3b4879bedbc9dcf9ad7674"/>
    </children>
    <children
        xsi:type="archimate:DiagramModelArchimateObject"
        id="id-03a8db7fb73f4994b4ab172aa1a0d9b4"
        fillColor="#2cfbeb">
      <bounds
          x="288"
          y="480"
          width="120"
          height="55"/>
      <archimateElement
          xsi:type="archimate:ApplicationComponent"
          href="ApplicationComponent_id-9561824bc15a40ed9be188788b60eca7.xml#id-9561824bc15a40ed9be188788b60eca7"/>
    </children>
    <children
        xsi:type="archimate:DiagramModelArchimateObject"
        id="id-3e60975ade1d4fd09527b9cb1b22be4f"
        fillColor="#2cfded">
      <bounds
          x="588"
          y="276"
          width="120"
          height="55"/>
      <archimateElement
          xsi:type="archimate:ApplicationComponent"
          href="ApplicationComponent_id-5145ce563c0644a486b979b63c8bf05b.xml#id-5145ce563c0644a486b979b63c8bf05b"/>
    </children>
    <children
        xsi:type="archimate:DiagramModelArchimateObject"
        id="id-f47a7cfa04e9427186ce26bb4dc16da2"
        fillColor="#2cfded">
      <bounds
          x="732"
          y="276"
          width="120"
          height="55"/>
      <archimateElement
          xsi:type="archimate:ApplicationComponent"
          href="ApplicationComponent_id-2a77a57051904fc2b4ef2b699845d6d1.xml#id-2a77a57051904fc2b4ef2b699845d6d1"/>
    </children>
    <children
        xsi:type="archimate:DiagramModelArchimateObject"
        id="id-1c9bdbc43514474dad4258088910a5ce"
        fillColor="#2cfded">
      <bounds
          x="876"
          y="276"
          width="120"
          height="55"/>
      <archimateElement
          xsi:type="archimate:ApplicationComponent"
          href="ApplicationComponent_id-bbceaae52b49401cb928e515c5c084f8.xml#id-bbceaae52b49401cb928e515c5c084f8"/>
    </children>
    <children
        xsi:type="archimate:DiagramModelArchimateObject"
        id="id-9d2a701185f441ae9c19c588416756fa"
        fillColor="#b4fffe">
      <bounds
          x="588"
          y="384"
          width="120"
          height="55"/>
      <archimateElement
          xsi:type="archimate:ApplicationComponent"
          href="ApplicationComponent_id-9eb6277a5b534871a35e16cccaf93188.xml#id-9eb6277a5b534871a35e16cccaf93188"/>
    </children>
    <children
        xsi:type="archimate:DiagramModelArchimateObject"
        id="id-3ec781352400492a8e0af0e2e0fb543d">
      <bounds
          x="732"
          y="384"
          width="120"
          height="55"/>
      <archimateElement
          xsi:type="archimate:ApplicationComponent"
          href="ApplicationComponent_id-b941042d9cd94624a6a2cade216f6614.xml#id-b941042d9cd94624a6a2cade216f6614"/>
    </children>
    <children
        xsi:type="archimate:DiagramModelArchimateObject"
        id="id-bcdf2fcab98c493a92d0654eaba94c35"
        fillColor="#2cfcec">
      <bounds
          x="876"
          y="384"
          width="120"
          height="55"/>
      <archimateElement
          xsi:type="archimate:ApplicationComponent"
          href="ApplicationComponent_id-163b958403c545de8a4b879a64b37cf8.xml#id-163b958403c545de8a4b879a64b37cf8"/>
    </children>
    <children
        xsi:type="archimate:DiagramModelArchimateObject"
        id="id-5c31b263df154c38a8b94f7ae9d8a87e">
      <bounds
          x="588"
          y="480"
          width="120"
          height="55"/>
      <archimateElement
          xsi:type="archimate:ApplicationComponent"
          href="ApplicationComponent_id-abaadbd44e8645cd848bf7e733754ac1.xml#id-abaadbd44e8645cd848bf7e733754ac1"/>
    </children>
    <children
        xsi:type="archimate:DiagramModelArchimateObject"
        id="id-48613f1b7d2646c19a2b77f701840876">
      <bounds
          x="588"
          y="576"
          width="120"
          height="55"/>
      <archimateElement
          xsi:type="archimate:ApplicationComponent"
          href="ApplicationComponent_id-b3a8d301d45e47ada11316a81a515ca0.xml#id-b3a8d301d45e47ada11316a81a515ca0"/>
    </children>
    <children
        xsi:type="archimate:DiagramModelArchimateObject"
        id="id-248a20cb7a854fee8bbcbc6f908f4c1b">
      <bounds
          x="732"
          y="480"
          width="120"
          height="55"/>
      <archimateElement
          xsi:type="archimate:ApplicationComponent"
          href="ApplicationComponent_id-5c9c535d9318453caa8b503c9b268f6b.xml#id-5c9c535d9318453caa8b503c9b268f6b"/>
    </children>
    <children
        xsi:type="archimate:DiagramModelArchimateObject"
        id="id-5ca2a27d0dcf4e45be68d02bd31f2f16"
        fillColor="#b3fffd">
      <bounds
          x="876"
          y="480"
          width="120"
          height="55"/>
      <archimateElement
          xsi:type="archimate:ApplicationComponent"
          href="ApplicationComponent_id-5c1ee23f97d445fc8a33abc6508b24c2.xml#id-5c1ee23f97d445fc8a33abc6508b24c2"/>
    </children>
    <children
        xsi:type="archimate:DiagramModelArchimateObject"
        id="id-713cf613edad42508c083bc276092383"
        fillColor="#b2fffc">
      <bounds
          x="876"
          y="576"
          width="120"
          height="55"/>
      <archimateElement
          xsi:type="archimate:ApplicationComponent"
          href="ApplicationComponent_id-10c03269fd954753893ee69daf3363a2.xml#id-10c03269fd954753893ee69daf3363a2"/>
    </children>
    <children
        xsi:type="archimate:DiagramModelArchimateObject"
        id="id-e65f8c5bc38d4a2a872f1e8be0b521b0">
      <bounds
          x="732"
          y="576"
          width="120"
          height="55"/>
      <archimateElement
          xsi:type="archimate:ApplicationComponent"
          href="ApplicationComponent_id-9e4f63b225a347fb83c2880232480944.xml#id-9e4f63b225a347fb83c2880232480944"/>
    </children>
    <children
        xsi:type="archimate:DiagramModelArchimateObject"
        id="id-d5f2535a96ee42c88066ea8d28c54a54">
      <bounds
          x="1008"
          y="480"
          width="120"
          height="55"/>
      <archimateElement
          xsi:type="archimate:ApplicationComponent"
          href="ApplicationComponent_id-5e42f08d93454980b505da0147813095.xml#id-5e42f08d93454980b505da0147813095"/>
    </children>
    <children
        xsi:type="archimate:DiagramModelArchimateObject"
        id="id-bb9839bfeca04b61bbdb93a760584324">
      <bounds
          x="1008"
          y="576"
          width="120"
          height="55"/>
      <archimateElement
          xsi:type="archimate:ApplicationComponent"
          href="ApplicationComponent_id-6b8a116825ea4f66a83a22c9fdbf9906.xml#id-6b8a116825ea4f66a83a22c9fdbf9906"/>
    </children>
    <children
        xsi:type="archimate:DiagramModelArchimateObject"
        id="id-e981dcb113dc49c695a8ebe4b54c385c"
        fillColor="#2cfbeb">
      <bounds
          x="588"
          y="660"
          width="120"
          height="55"/>
      <archimateElement
          xsi:type="archimate:ApplicationComponent"
          href="ApplicationComponent_id-35a10343d2e0430380b84434fd42c849.xml#id-35a10343d2e0430380b84434fd42c849"/>
    </children>
    <children
        xsi:type="archimate:DiagramModelArchimateObject"
        id="id-794ccf901f82470fbd0747c534dec030"
        fillColor="#2bfaea">
      <bounds
          x="732"
          y="660"
          width="120"
          height="55"/>
      <archimateElement
          xsi:type="archimate:ApplicationComponent"
          href="ApplicationComponent_id-11c08c06e582495b977c9d8e22f8867c.xml#id-11c08c06e582495b977c9d8e22f8867c"/>
    </children>
    <children
        xsi:type="archimate:DiagramModelArchimateObject"
        id="id-c7de3a96b0f84bde9e71bcc5476f822e"
        fillColor="#b4fffe">
      <bounds
          x="1164"
          y="274"
          width="120"
          height="55"/>
      <archimateElement
          xsi:type="archimate:ApplicationComponent"
          href="ApplicationComponent_id-96b6435afbca4f429cf88949335c13a0.xml#id-96b6435afbca4f429cf88949335c13a0"/>
    </children>
    <children
        xsi:type="archimate:DiagramModelArchimateObject"
        id="id-345684bb13c841b6a2ff34e5c56cac31">
      <bounds
          x="1296"
          y="274"
          width="120"
          height="55"/>
      <archimateElement
          xsi:type="archimate:ApplicationComponent"
          href="ApplicationComponent_id-ed12bf44db464f56a6e1501911a0f6e4.xml#id-ed12bf44db464f56a6e1501911a0f6e4"/>
    </children>
    <children
        xsi:type="archimate:DiagramModelArchimateObject"
        id="id-8b8d3a88f9ab41babde611e5cdf190bc"
        fillColor="#b4fffe">
      <bounds
          x="1428"
          y="274"
          width="120"
          height="55"/>
      <archimateElement
          xsi:type="archimate:ApplicationComponent"
          href="ApplicationComponent_id-c84c9ed7b9ea41efb6af06423db1abe9.xml#id-c84c9ed7b9ea41efb6af06423db1abe9"/>
    </children>
    <children
        xsi:type="archimate:DiagramModelArchimateObject"
        id="id-c1032102402849168072a37019c0a247"
        textPosition="1">
      <bounds
          x="1716"
          y="72"
          width="120"
          height="55"/>
      <archimateElement
          xsi:type="archimate:Capability"
          href="Capability_id-347311d41ce949c7932776f3cb24477f.xml#id-347311d41ce949c7932776f3cb24477f"/>
    </children>
    <children
        xsi:type="archimate:DiagramModelArchimateObject"
        id="id-0a50d85b91c44846a26aa5d2e2b40ec6"
        fillColor="#2cfded">
      <bounds
          x="1716"
          y="274"
          width="120"
          height="55"/>
      <archimateElement
          xsi:type="archimate:ApplicationComponent"
          href="ApplicationComponent_id-0f4d3665db6d4700b56cd52e48f0a2d1.xml#id-0f4d3665db6d4700b56cd52e48f0a2d1"/>
    </children>
    <children
        xsi:type="archimate:DiagramModelArchimateObject"
        id="id-b3bde5162bbf44cdb0aef1c3b1ff41c2"
        fillColor="#2bf9e9">
      <bounds
          x="876"
          y="660"
          width="120"
          height="55"/>
      <archimateElement
          xsi:type="archimate:ApplicationComponent"
          href="ApplicationComponent_id-e65f6d8797f24b7bae09d037b29d78ff.xml#id-e65f6d8797f24b7bae09d037b29d78ff"/>
    </children>
    <archimateElement
        xsi:type="archimate:Grouping"
        href="Grouping_id-98f5e9c47d424ae3a330b10ad905139a.xml#id-98f5e9c47d424ae3a330b10ad905139a"/>
  </children>
  <children
      xsi:type="archimate:DiagramModelArchimateObject"
      id="id-b52f799c75644da68fa56daf00de06d2">
    <bounds
        x="-432"
        y="505"
        width="120"
        height="55"/>
    <archimateElement
        xsi:type="archimate:ApplicationComponent"
        href="ApplicationComponent_id-6caaa3da3f604c5dbd061e2af0836253.xml#id-6caaa3da3f604c5dbd061e2af0836253"/>
  </children>
  <children
      xsi:type="archimate:DiagramModelArchimateObject"
      id="id-0bb2fb9fa73c4cdc9f6fb31cef3223da"
      fillColor="#2cfded">
    <bounds
        x="-275"
        y="395"
        width="120"
        height="55"/>
    <archimateElement
        xsi:type="archimate:ApplicationComponent"
        href="ApplicationComponent_id-23eb47c1f57a403fa26db1e914d03bf9.xml#id-23eb47c1f57a403fa26db1e914d03bf9"/>
  </children>
  <children
      xsi:type="archimate:DiagramModelArchimateObject"
      id="id-0c564f725b2640c78fb010034d4f9636"
      fillColor="#2cfbeb">
    <bounds
        x="-768"
        y="395"
        width="120"
        height="55"/>
    <archimateElement
        xsi:type="archimate:ApplicationComponent"
        href="ApplicationComponent_id-f235b053bd114eeba6b7a13ba00a3556.xml#id-f235b053bd114eeba6b7a13ba00a3556"/>
  </children>
  <children
      xsi:type="archimate:DiagramModelArchimateObject"
      id="id-a1b8abe035f643c88b33f783d18c347c"
      fillColor="#2cfded">
    <bounds
        x="-144"
        y="395"
        width="120"
        height="55"/>
    <archimateElement
        xsi:type="archimate:ApplicationComponent"
        href="ApplicationComponent_id-3d77b13a9316471f972ccb15fc96c3e2.xml#id-3d77b13a9316471f972ccb15fc96c3e2"/>
  </children>
  <children
      xsi:type="archimate:DiagramModelArchimateObject"
      id="id-df3cabe0a21b47d5a54f512385a18901"
      fillColor="#2cfded">
    <bounds
        x="3072"
        y="395"
        width="120"
        height="55"/>
    <archimateElement
        xsi:type="archimate:ApplicationComponent"
        href="ApplicationComponent_id-c2acfc832a2c4f8899af48b1a0b763e4.xml#id-c2acfc832a2c4f8899af48b1a0b763e4"/>
  </children>
  <children
      xsi:type="archimate:DiagramModelArchimateObject"
      id="id-8627df37ea0e4ec9895ee5253c674c5b"
      fillColor="#b4fffe">
    <bounds
        x="3252"
        y="395"
        width="120"
        height="55"/>
    <archimateElement
        xsi:type="archimate:ApplicationComponent"
        href="ApplicationComponent_id-723f46c3a2c24aa6946fdd92dcb74d90.xml#id-723f46c3a2c24aa6946fdd92dcb74d90"/>
  </children>
  <children
      xsi:type="archimate:DiagramModelArchimateObject"
      id="id-51d6ed51bff9422581a59d950d62327c">
    <bounds
        x="142"
        y="401"
        width="120"
        height="55"/>
    <archimateElement
        xsi:type="archimate:ApplicationComponent"
        href="ApplicationComponent_id-046b08c2a20b4226a0f17f845c9634c3.xml#id-046b08c2a20b4226a0f17f845c9634c3"/>
  </children>
  <children
      xsi:type="archimate:DiagramModelArchimateObject"
      id="id-3257029c8f8d47d5a8b63372cc54e3bb"
      fillColor="#2cfded">
    <bounds
        x="276"
        y="399"
        width="120"
        height="55"/>
    <archimateElement
        xsi:type="archimate:ApplicationComponent"
        href="ApplicationComponent_id-316759c590484c5f80864641ef237c1a.xml#id-316759c590484c5f80864641ef237c1a"/>
  </children>
  <children
      xsi:type="archimate:DiagramModelArchimateObject"
      id="id-fef21ddafc8e4f3f9318c9d87a2de0d3"
      fillColor="#2cfded">
    <bounds
        x="420"
        y="399"
        width="120"
        height="55"/>
    <archimateElement
        xsi:type="archimate:ApplicationComponent"
        href="ApplicationComponent_id-31bc637bcf86464bbea580d6a9bee412.xml#id-31bc637bcf86464bbea580d6a9bee412"/>
  </children>
  <children
      xsi:type="archimate:DiagramModelNote"
      id="id-b846369408ad4146a35c7f657b875ba2"
      font="1|Lucida Grande|14.0|1|COCOA|1|LucidaGrande-Bold"
      textAlignment="1"
      content="CIRION&#xA;&#xA;Service Assurance / Datacenter / IT Architecture &#xD;&#xA;&#xD;&#xA;DAY 1">
    <bounds
        x="-780"
        y="12"
        width="325"
        height="85"/>
  </children>
  <children
      xsi:type="archimate:DiagramModelArchimateObject"
      id="id-1e8b2b2d0b4e49f4bfb0e40860380a79">
    <bounds
        x="-618"
        y="397"
        width="120"
        height="55"/>
    <archimateElement
        xsi:type="archimate:ApplicationComponent"
        href="ApplicationComponent_id-e48c3260a0044296abaf8e8f14a32a62.xml#id-e48c3260a0044296abaf8e8f14a32a62"/>
  </children>
  <children
      xsi:type="archimate:DiagramModelArchimateObject"
      id="id-05800e5100984c3b8b23a7b7f66c6bf7"
      textPosition="1">
    <bounds
        x="1320"
        y="192"
        width="960"
        height="55"/>
    <archimateElement
        xsi:type="archimate:Capability"
        href="Capability_id-02d5ce3e977e4e898042be6143c24d4c.xml#id-02d5ce3e977e4e898042be6143c24d4c"/>
  </children>
  <children
      xsi:type="archimate:DiagramModelArchimateObject"
      id="id-d222d671cff549e59a544f8b5ccf35fd"
      textPosition="1">
    <bounds
        x="2616"
        y="195"
        width="120"
        height="55"/>
    <archimateElement
        xsi:type="archimate:Capability"
        href="Capability_id-3cbe20226f2548018883a971d549535c.xml#id-3cbe20226f2548018883a971d549535c"/>
  </children>
  <children
      xsi:type="archimate:DiagramModelArchimateObject"
      id="id-561b179a6887416988ebfa7a46772fb4"
      textPosition="1">
    <bounds
        x="-768"
        y="194"
        width="120"
        height="55"/>
    <archimateElement
        xsi:type="archimate:Capability"
        href="Capability_id-51f9229a4820419a85d644886e5f9fb7.xml#id-51f9229a4820419a85d644886e5f9fb7"/>
  </children>
  <children
      xsi:type="archimate:DiagramModelArchimateObject"
      id="id-e01a60bbe3fc4629840d2e564034bfc5"
      textPosition="1">
    <bounds
        x="-618"
        y="194"
        width="120"
        height="55"/>
    <archimateElement
        xsi:type="archimate:Capability"
        href="Capability_id-a125ee88589840179ad8311f734f4baa.xml#id-a125ee88589840179ad8311f734f4baa"/>
  </children>
  <children
      xsi:type="archimate:DiagramModelArchimateObject"
      id="id-f7080f5b9f714de29e7799f6cafaf3f3"
      textPosition="1">
    <bounds
        x="2942"
        y="194"
        width="120"
        height="55"/>
    <archimateElement
        xsi:type="archimate:Capability"
        href="Capability_id-2799992890e34c87b521e0cb093d4c5c.xml#id-2799992890e34c87b521e0cb093d4c5c"/>
  </children>
  <children
      xsi:type="archimate:DiagramModelArchimateObject"
      id="id-b92f59e8398a4466976c9081305a9d8f"
      textPosition="1">
    <bounds
        x="17"
        y="198"
        width="120"
        height="55"/>
    <archimateElement
        xsi:type="archimate:Capability"
        href="Capability_id-05136cbce38f4994a956728c4c92b058.xml#id-05136cbce38f4994a956728c4c92b058"/>
  </children>
  <children
      xsi:type="archimate:DiagramModelArchimateObject"
      id="id-3e5f658686364b229314b5f00537ca37"
      textPosition="1">
    <bounds
        x="142"
        y="198"
        width="120"
        height="55"/>
    <archimateElement
        xsi:type="archimate:Capability"
        href="Capability_id-2ab2a4cc361f41219c5ed080f0f73384.xml#id-2ab2a4cc361f41219c5ed080f0f73384"/>
  </children>
  <children
      xsi:type="archimate:DiagramModelArchimateObject"
      id="id-b61b03bc696442d3b26ae920e5b0359a"
      textPosition="1">
    <bounds
        x="17"
        y="263"
        width="120"
        height="55"/>
    <archimateElement
        xsi:type="archimate:Capability"
        href="Capability_id-b553650551654a25bd15d142c1bc44d3.xml#id-b553650551654a25bd15d142c1bc44d3"/>
  </children>
  <children
      xsi:type="archimate:DiagramModelArchimateObject"
      id="id-04f258a1a8c04333a20ccbbbedd7cc34"
      textPosition="1">
    <bounds
        x="-618"
        y="259"
        width="120"
        height="55"/>
    <archimateElement
        xsi:type="archimate:Capability"
        href="Capability_id-b162c75676284897a3a19f2618d44f4c.xml#id-b162c75676284897a3a19f2618d44f4c"/>
  </children>
  <children
      xsi:type="archimate:DiagramModelArchimateObject"
      id="id-28fdb910eb88440f82f6f471151ea8eb"
      textPosition="1">
    <bounds
        x="1896"
        y="257"
        width="384"
        height="55"/>
    <archimateElement
        xsi:type="archimate:Capability"
        href="Capability_id-5cda00e77edd4818ab600ace1ebc4343.xml#id-5cda00e77edd4818ab600ace1ebc4343"/>
  </children>
  <children
      xsi:type="archimate:DiagramModelArchimateObject"
      id="id-ecf15420e9254eab9d4c9bfe10d210f9"
      textPosition="1">
    <bounds
        x="1320"
        y="257"
        width="552"
        height="55"/>
    <archimateElement
        xsi:type="archimate:Capability"
        href="Capability_id-a54be08134b84f6ba0e2e0dbc6ca182f.xml#id-a54be08134b84f6ba0e2e0dbc6ca182f"/>
  </children>
  <children
      xsi:type="archimate:DiagramModelArchimateObject"
      id="id-88730430a9974c41b3e46f00ed7cdf76"
      textPosition="1">
    <bounds
        x="276"
        y="198"
        width="420"
        height="55"/>
    <archimateElement
        xsi:type="archimate:Capability"
        href="Capability_id-d68dbaf7b70c491b82f869def41173f4.xml#id-d68dbaf7b70c491b82f869def41173f4"/>
  </children>
  <children
      xsi:type="archimate:DiagramModelArchimateObject"
      id="id-dc0b9f4d2c19483baba52949aa74893b"
      textPosition="1">
    <bounds
        x="420"
        y="263"
        width="276"
        height="55"/>
    <archimateElement
        xsi:type="archimate:Capability"
        href="Capability_id-bcdf56353509436c85f9cd2ae867a0dd.xml#id-bcdf56353509436c85f9cd2ae867a0dd"/>
  </children>
  <children
      xsi:type="archimate:DiagramModelArchimateObject"
      id="id-72f6d14d723747bb8d9a5e3836a2050d"
      textPosition="1">
    <bounds
        x="3072"
        y="194"
        width="120"
        height="55"/>
    <archimateElement
        xsi:type="archimate:Capability"
        href="Capability_id-389cc23327c94595bc5e4b01d2790ede.xml#id-389cc23327c94595bc5e4b01d2790ede"/>
  </children>
  <children
      xsi:type="archimate:DiagramModelArchimateObject"
      id="id-ce07f93184fa4c08bdba7eeb4f2b4657"
      fillColor="#2cfbeb">
    <bounds
        x="2622"
        y="398"
        width="120"
        height="55"/>
    <archimateElement
        xsi:type="archimate:ApplicationComponent"
        href="ApplicationComponent_id-72317827abb3474ca374454466fc9874.xml#id-72317827abb3474ca374454466fc9874"/>
  </children>
  <children
      xsi:type="archimate:DiagramModelNote"
      id="id-acaf39e8d8c84ce9967f6d3217992e83"
      textAlignment="1"
      fillColor="#ff7d78"
      content="Day 1">
    <bounds
        x="-432"
        y="12"
        width="84"
        height="30"/>
  </children>
  <children
      xsi:type="archimate:DiagramModelNote"
      id="id-220f9b227c624d0292729a8ce40f9d8d"
      textAlignment="1"
      fillColor="#2cfded"
      content="Cirion">
    <bounds
        x="-336"
        y="52"
        width="84"
        height="30"/>
  </children>
  <children
      xsi:type="archimate:DiagramModelNote"
      id="id-c750dbb18732451786d0c5099bbbf5e7"
      textAlignment="1"
      fillColor="#b4fffe"
      content="TSA - USA">
    <bounds
        x="-432"
        y="52"
        width="84"
        height="30"/>
  </children>
  <children
      xsi:type="archimate:DiagramModelNote"
      id="id-8e1d1056c6f643e0b7c71957f570c1b4"
      textAlignment="1"
      fillColor="#00f900"
      content="Cirion TBM&#xA;">
    <bounds
        x="-240"
        y="52"
        width="84"
        height="30"/>
  </children>
</archimate:ArchimateDiagramModel>
